{
  "id": 308191,
  "slug": "308191-eternal-sword",
  "type": "GEAR",
  "name": {
    "zh": "永恒之剑",
    "en": "Eternal Sword"
  },
  "description": {
    "zh": "",
    "en": ""
  },
  "icon": "/game/game/gear/sword/SWORD_300019.png",
  "image": "/game/game/gear/sword/SWORD_300019.png",
  "grade": "DIVINE",
  "gear": "SWORD",
  "level": 90,
  "gameVersion": "game-v1",
  "updatedAt": "2026-06-25T06:33:46.622Z",
  "source": "local-json",
  "marketable": false,
  "removed": false,
  "confidence": "datamined",
  "detail": {
    "desc": null,
    "stats": {
      "GearKey": 308191,
      "BaseStat1_Value": 2555,
      "BaseStat2_Value": 57,
      "InherentStat1_STATTYPE": "AttackDamage",
      "InherentStat1_MODTYPE": "FLAT",
      "InherentStat1_Value": 500,
      "InherentStat2_STATTYPE": "AttackDamage",
      "InherentStat2_MODTYPE": "ADDITIVE",
      "InherentStat2_Value": 2000,
      "InherentStat3_STATTYPE": "CriticalDamage",
      "InherentStat3_MODTYPE": "FLAT",
      "InherentStat3_Value": 1500,
      "UniqueModKey": null
    },
    "synthType": "Gear",
    "dropKey": null,
    "uniqueMod": null,
    "sellGold": 124665654,
    "cubeExp": 62151660
  }
}