{
  "id": 335192,
  "slug": "335192-eternal-scepter",
  "type": "GEAR",
  "name": {
    "zh": "永恒权杖",
    "en": "Eternal Scepter"
  },
  "description": {
    "zh": "",
    "en": ""
  },
  "icon": "/game/game/gear/scepter/SCEPTER_330019.png",
  "image": "/game/game/gear/scepter/SCEPTER_330019.png",
  "grade": "ARCANA",
  "gear": "SCEPTER",
  "level": 90,
  "gameVersion": "game-v1",
  "updatedAt": "2026-06-24T07:09:17.476Z",
  "source": "local-json",
  "marketable": false,
  "removed": false,
  "confidence": "datamined",
  "detail": {
    "desc": null,
    "stats": {
      "GearKey": 335192,
      "BaseStat1_Value": 923,
      "BaseStat2_Value": 24,
      "InherentStat1_STATTYPE": "AttackDamage",
      "InherentStat1_MODTYPE": "FLAT",
      "InherentStat1_Value": 251,
      "InherentStat2_STATTYPE": "CriticalDamage",
      "InherentStat2_MODTYPE": "FLAT",
      "InherentStat2_Value": 1038,
      "InherentStat3_STATTYPE": "AttackDamage",
      "InherentStat3_MODTYPE": "ADDITIVE",
      "InherentStat3_Value": 1307,
      "UniqueModKey": null
    },
    "synthType": "Gear",
    "dropKey": null,
    "uniqueMod": null,
    "sellGold": 3180384,
    "cubeExp": 1585080
  }
}