{
  "id": 340010,
  "slug": "340010-large-crossbow",
  "type": "GEAR",
  "name": {
    "zh": "大型弩",
    "en": "Large Crossbow"
  },
  "description": {
    "zh": "",
    "en": ""
  },
  "icon": "/game/game/gear/crossbow/CROSSBOW_340010.png",
  "image": "/game/game/gear/crossbow/CROSSBOW_340010.png",
  "grade": "COMMON",
  "gear": "CROSSBOW",
  "level": 45,
  "gameVersion": "game-v1",
  "updatedAt": "2026-06-24T07:09:17.476Z",
  "source": "local-json",
  "marketable": false,
  "removed": false,
  "confidence": "datamined",
  "detail": {
    "desc": null,
    "stats": {
      "GearKey": 340010,
      "BaseStat1_Value": 92,
      "BaseStat2_Value": 20,
      "InherentStat1_STATTYPE": "NONE",
      "InherentStat1_MODTYPE": "FLAT",
      "InherentStat1_Value": 0,
      "InherentStat2_STATTYPE": "NONE",
      "InherentStat2_MODTYPE": "FLAT",
      "InherentStat2_Value": 0,
      "InherentStat3_STATTYPE": "NONE",
      "InherentStat3_MODTYPE": "FLAT",
      "InherentStat3_Value": 0,
      "UniqueModKey": null
    },
    "synthType": "Gear",
    "dropKey": null,
    "uniqueMod": null,
    "sellGold": 5920,
    "cubeExp": 2448
  }
}