{
  "id": 342051,
  "slug": "342051-exceptional-crossbow",
  "type": "GEAR",
  "name": {
    "zh": "卓越弩",
    "en": "Exceptional Crossbow"
  },
  "description": {
    "zh": "",
    "en": ""
  },
  "icon": "/game/game/gear/crossbow/CROSSBOW_340005.png",
  "image": "/game/game/gear/crossbow/CROSSBOW_340005.png",
  "grade": "RARE",
  "gear": "CROSSBOW",
  "level": 20,
  "gameVersion": "game-v1",
  "updatedAt": "2026-06-03T11:43:00.360Z",
  "source": "local-json",
  "marketable": false,
  "removed": false,
  "confidence": "datamined",
  "detail": {
    "desc": null,
    "stats": {
      "GearKey": 342051,
      "BaseStat1_Value": 30,
      "BaseStat2_Value": 20,
      "InherentStat1_STATTYPE": "AttackSpeed",
      "InherentStat1_MODTYPE": "MULTIPLICATIVE",
      "InherentStat1_Value": 86,
      "InherentStat2_STATTYPE": "NONE",
      "InherentStat2_MODTYPE": "FLAT",
      "InherentStat2_Value": 0,
      "InherentStat3_STATTYPE": "NONE",
      "InherentStat3_MODTYPE": "FLAT",
      "InherentStat3_Value": 0,
      "UniqueModKey": null
    },
    "synthType": "Gear",
    "dropKey": null,
    "uniqueMod": null,
    "sellGold": 19800,
    "cubeExp": 4320
  }
}