{
  "id": 344171,
  "slug": "344171-dimensional-crossbow",
  "type": "GEAR",
  "name": {
    "zh": "次元弩",
    "en": "Dimensional Crossbow"
  },
  "description": {
    "zh": "",
    "en": ""
  },
  "icon": "/game/game/gear/crossbow/CROSSBOW_340017.png",
  "image": "/game/game/gear/crossbow/CROSSBOW_340017.png",
  "grade": "IMMORTAL",
  "gear": "CROSSBOW",
  "level": 80,
  "gameVersion": "game-v1",
  "updatedAt": "2026-06-25T06:33:46.622Z",
  "source": "local-json",
  "marketable": true,
  "removed": false,
  "confidence": "datamined",
  "detail": {
    "desc": null,
    "stats": {
      "GearKey": 344171,
      "BaseStat1_Value": 858,
      "BaseStat2_Value": 20,
      "InherentStat1_STATTYPE": "AttackSpeed",
      "InherentStat1_MODTYPE": "MULTIPLICATIVE",
      "InherentStat1_Value": 192,
      "InherentStat2_STATTYPE": "AttackDamage",
      "InherentStat2_MODTYPE": "FLAT",
      "InherentStat2_Value": 144,
      "InherentStat3_STATTYPE": "NONE",
      "InherentStat3_MODTYPE": "FLAT",
      "InherentStat3_Value": 0,
      "UniqueModKey": null
    },
    "synthType": "Gear",
    "dropKey": null,
    "uniqueMod": null,
    "sellGold": 907200,
    "cubeExp": 429624
  }
}