{
  "id": 346092,
  "slug": "346092-elite-crossbow",
  "type": "GEAR",
  "name": {
    "zh": "精英弩",
    "en": "Elite Crossbow"
  },
  "description": {
    "zh": "",
    "en": ""
  },
  "icon": "/game/game/gear/crossbow/CROSSBOW_340009.png",
  "image": "/game/game/gear/crossbow/CROSSBOW_340009.png",
  "grade": "BEYOND",
  "gear": "CROSSBOW",
  "level": 40,
  "gameVersion": "game-v1",
  "updatedAt": "2026-06-24T07:09:17.476Z",
  "source": "local-json",
  "marketable": false,
  "removed": false,
  "confidence": "datamined",
  "detail": {
    "desc": null,
    "stats": {
      "GearKey": 346092,
      "BaseStat1_Value": 452,
      "BaseStat2_Value": 28,
      "InherentStat1_STATTYPE": "AttackSpeed",
      "InherentStat1_MODTYPE": "MULTIPLICATIVE",
      "InherentStat1_Value": 152,
      "InherentStat2_STATTYPE": "AttackDamage",
      "InherentStat2_MODTYPE": "ADDITIVE",
      "InherentStat2_Value": 678,
      "InherentStat3_STATTYPE": "CriticalDamage",
      "InherentStat3_MODTYPE": "FLAT",
      "InherentStat3_Value": 619,
      "UniqueModKey": null
    },
    "synthType": "Gear",
    "dropKey": null,
    "uniqueMod": null,
    "sellGold": 4304586,
    "cubeExp": 1691160
  }
}