{
  "id": 422092,
  "slug": "422092-arcane-orb",
  "type": "GEAR",
  "name": {
    "zh": "奥术法球",
    "en": "Arcane Orb"
  },
  "description": {
    "zh": "",
    "en": ""
  },
  "icon": "/game/game/gear/orb/ORB_420009.png",
  "image": "/game/game/gear/orb/ORB_420009.png",
  "grade": "RARE",
  "gear": "ORB",
  "level": 40,
  "gameVersion": "game-v1",
  "updatedAt": "2026-06-25T06:33:46.622Z",
  "source": "local-json",
  "marketable": false,
  "removed": false,
  "confidence": "datamined",
  "detail": {
    "desc": null,
    "stats": {
      "GearKey": 422092,
      "BaseStat1_Value": 160,
      "BaseStat2_Value": 0,
      "InherentStat1_STATTYPE": "CooldownReduction",
      "InherentStat1_MODTYPE": "FLAT",
      "InherentStat1_Value": 26,
      "InherentStat2_STATTYPE": "NONE",
      "InherentStat2_MODTYPE": "FLAT",
      "InherentStat2_Value": 0,
      "InherentStat3_STATTYPE": "NONE",
      "InherentStat3_MODTYPE": "FLAT",
      "InherentStat3_Value": 0,
      "UniqueModKey": null
    },
    "synthType": "Gear",
    "dropKey": null,
    "uniqueMod": null,
    "sellGold": 93420,
    "cubeExp": 36720
  }
}