{
  "id": 426162,
  "slug": "426162-void-orb",
  "type": "GEAR",
  "name": {
    "zh": "虚空法球",
    "en": "Void Orb"
  },
  "description": {
    "zh": "",
    "en": ""
  },
  "icon": "/game/game/gear/orb/ORB_420016.png",
  "image": "/game/game/gear/orb/ORB_420016.png",
  "grade": "BEYOND",
  "gear": "ORB",
  "level": 75,
  "gameVersion": "game-v1",
  "updatedAt": "2026-06-03T11:43:00.360Z",
  "source": "local-json",
  "marketable": false,
  "removed": false,
  "confidence": "datamined",
  "detail": {
    "desc": null,
    "stats": {
      "GearKey": 426162,
      "BaseStat1_Value": 284,
      "BaseStat2_Value": null,
      "InherentStat1_STATTYPE": "CriticalDamage",
      "InherentStat1_MODTYPE": "FLAT",
      "InherentStat1_Value": 647,
      "InherentStat2_STATTYPE": "AttackDamage",
      "InherentStat2_MODTYPE": "ADDITIVE",
      "InherentStat2_Value": 647,
      "InherentStat3_STATTYPE": "AttackDamage",
      "InherentStat3_MODTYPE": "FLAT",
      "InherentStat3_Value": 121,
      "UniqueModKey": null
    },
    "synthType": "Gear",
    "dropKey": null,
    "uniqueMod": null,
    "sellGold": 17483752,
    "cubeExp": 8117568
  }
}