{
  "id": 432161,
  "slug": "432161-crystal-tome",
  "type": "GEAR",
  "name": {
    "zh": "水晶魔法书",
    "en": "Crystal Tome"
  },
  "description": {
    "zh": "",
    "en": ""
  },
  "icon": "/game/game/gear/tome/TOME_430016.png",
  "image": "/game/game/gear/tome/TOME_430016.png",
  "grade": "RARE",
  "gear": "TOME",
  "level": 75,
  "gameVersion": "game-v1",
  "updatedAt": "2026-06-03T11:43:00.360Z",
  "source": "local-json",
  "marketable": false,
  "removed": false,
  "confidence": "datamined",
  "detail": {
    "desc": null,
    "stats": {
      "GearKey": 432161,
      "BaseStat1_Value": 257,
      "BaseStat2_Value": null,
      "InherentStat1_STATTYPE": "BlockChance",
      "InherentStat1_MODTYPE": "FLAT",
      "InherentStat1_Value": 75,
      "InherentStat2_STATTYPE": "NONE",
      "InherentStat2_MODTYPE": "FLAT",
      "InherentStat2_Value": 0,
      "InherentStat3_STATTYPE": "NONE",
      "InherentStat3_MODTYPE": "FLAT",
      "InherentStat3_Value": 0,
      "UniqueModKey": null
    },
    "synthType": "Gear",
    "dropKey": null,
    "uniqueMod": null,
    "sellGold": 189720,
    "cubeExp": 88128
  }
}