{
  "id": 454011,
  "slug": "454011-short-hatchet",
  "type": "GEAR",
  "name": {
    "zh": "短手斧",
    "en": "Short Hatchet"
  },
  "description": {
    "zh": "",
    "en": ""
  },
  "icon": "/game/game/gear/hatchet/HATCHET_450001.png",
  "image": "/game/game/gear/hatchet/HATCHET_450001.png",
  "grade": "IMMORTAL",
  "gear": "HATCHET",
  "level": 1,
  "gameVersion": "game-v1",
  "updatedAt": "2026-06-25T06:33:46.622Z",
  "source": "local-json",
  "marketable": true,
  "removed": false,
  "confidence": "datamined",
  "detail": {
    "desc": null,
    "stats": {
      "GearKey": 454011,
      "BaseStat1_Value": 265,
      "BaseStat2_Value": null,
      "InherentStat1_STATTYPE": "CriticalChance",
      "InherentStat1_MODTYPE": "ADDITIVE",
      "InherentStat1_Value": 155,
      "InherentStat2_STATTYPE": "CooldownReduction",
      "InherentStat2_MODTYPE": "FLAT",
      "InherentStat2_Value": 21,
      "InherentStat3_STATTYPE": "NONE",
      "InherentStat3_MODTYPE": "FLAT",
      "InherentStat3_Value": 0,
      "UniqueModKey": null
    },
    "synthType": "Gear",
    "dropKey": null,
    "uniqueMod": null,
    "sellGold": 1620,
    "cubeExp": 324
  }
}