{
  "id": 534021,
  "slug": "534021-empire-boots",
  "type": "GEAR",
  "name": {
    "zh": "帝国靴子",
    "en": "Empire Boots"
  },
  "description": {
    "zh": "",
    "en": ""
  },
  "icon": "/game/game/gear/boots/BOOTS_530002.png",
  "image": "/game/game/gear/boots/BOOTS_530002.png",
  "grade": "IMMORTAL",
  "gear": "BOOTS",
  "level": 5,
  "gameVersion": "game-v1",
  "updatedAt": "2026-06-24T07:09:17.476Z",
  "source": "local-json",
  "marketable": true,
  "removed": false,
  "confidence": "datamined",
  "detail": {
    "desc": null,
    "stats": {
      "GearKey": 534021,
      "BaseStat1_Value": 37,
      "BaseStat2_Value": null,
      "InherentStat1_STATTYPE": "Armor",
      "InherentStat1_MODTYPE": "FLAT",
      "InherentStat1_Value": 11,
      "InherentStat2_STATTYPE": "MovementSpeed",
      "InherentStat2_MODTYPE": "FLAT",
      "InherentStat2_Value": 35,
      "InherentStat3_STATTYPE": "NONE",
      "InherentStat3_MODTYPE": "FLAT",
      "InherentStat3_Value": 0,
      "UniqueModKey": null
    },
    "synthType": "Gear",
    "dropKey": null,
    "uniqueMod": null,
    "sellGold": 2835,
    "cubeExp": 1134
  }
}