{
  "id": 622091,
  "slug": "622091-amethyst-ring",
  "type": "GEAR",
  "name": {
    "zh": "紫水晶戒指",
    "en": "Amethyst Ring"
  },
  "description": {
    "zh": "",
    "en": ""
  },
  "icon": "/game/game/gear/ring/RING_620009.png",
  "image": "/game/game/gear/ring/RING_620009.png",
  "grade": "RARE",
  "gear": "RING",
  "level": 40,
  "gameVersion": "game-v1",
  "updatedAt": "2026-06-25T06:33:46.622Z",
  "source": "local-json",
  "marketable": false,
  "removed": false,
  "confidence": "datamined",
  "detail": {
    "desc": null,
    "stats": {
      "GearKey": 622091,
      "BaseStat1_Value": 0,
      "BaseStat2_Value": 0,
      "InherentStat1_STATTYPE": "AttackSpeed",
      "InherentStat1_MODTYPE": "ADDITIVE",
      "InherentStat1_Value": 65,
      "InherentStat2_STATTYPE": "NONE",
      "InherentStat2_MODTYPE": "FLAT",
      "InherentStat2_Value": 0,
      "InherentStat3_STATTYPE": "NONE",
      "InherentStat3_MODTYPE": "FLAT",
      "InherentStat3_Value": 0,
      "UniqueModKey": null
    },
    "synthType": "Accessory",
    "dropKey": null,
    "uniqueMod": null,
    "sellGold": 140130,
    "cubeExp": 55080
  }
}