{
  "id": 625161,
  "slug": "625161-astral-ring",
  "type": "GEAR",
  "name": {
    "zh": "星界戒指",
    "en": "Astral Ring"
  },
  "description": {
    "zh": "",
    "en": ""
  },
  "icon": "/game/game/gear/ring/RING_620016.png",
  "image": "/game/game/gear/ring/RING_620016.png",
  "grade": "ARCANA",
  "gear": "RING",
  "level": 75,
  "gameVersion": "game-v1",
  "updatedAt": "2026-06-25T06:33:46.622Z",
  "source": "local-json",
  "marketable": false,
  "removed": false,
  "confidence": "datamined",
  "detail": {
    "desc": null,
    "stats": {
      "GearKey": 625161,
      "BaseStat1_Value": 0,
      "BaseStat2_Value": null,
      "InherentStat1_STATTYPE": "CooldownReduction",
      "InherentStat1_MODTYPE": "FLAT",
      "InherentStat1_Value": 49,
      "InherentStat2_STATTYPE": "CriticalDamage",
      "InherentStat2_MODTYPE": "FLAT",
      "InherentStat2_Value": 283,
      "InherentStat3_STATTYPE": "AttackDamage",
      "InherentStat3_MODTYPE": "FLAT",
      "InherentStat3_Value": 54,
      "UniqueModKey": null
    },
    "synthType": "Accessory",
    "dropKey": null,
    "uniqueMod": null,
    "sellGold": 8195904,
    "cubeExp": 3804192
  }
}