{
  "id": 628142,
  "slug": "628142-eclipse-ring",
  "type": "GEAR",
  "name": {
    "zh": "蚀月戒指",
    "en": "Eclipse Ring"
  },
  "description": {
    "zh": "",
    "en": ""
  },
  "icon": "/game/game/gear/ring/RING_620014.png",
  "image": "/game/game/gear/ring/RING_620014.png",
  "grade": "DIVINE",
  "gear": "RING",
  "level": 65,
  "gameVersion": "game-v1",
  "updatedAt": "2026-06-24T07:09:17.476Z",
  "source": "local-json",
  "marketable": false,
  "removed": false,
  "confidence": "datamined",
  "detail": {
    "desc": null,
    "stats": {
      "GearKey": 628142,
      "BaseStat1_Value": 0,
      "BaseStat2_Value": null,
      "InherentStat1_STATTYPE": "CooldownReduction",
      "InherentStat1_MODTYPE": "FLAT",
      "InherentStat1_Value": 62,
      "InherentStat2_STATTYPE": "CriticalDamage",
      "InherentStat2_MODTYPE": "FLAT",
      "InherentStat2_Value": 377,
      "InherentStat3_STATTYPE": "AddHpPerKill",
      "InherentStat3_MODTYPE": "FLAT",
      "InherentStat3_Value": 72,
      "UniqueModKey": null
    },
    "synthType": "Accessory",
    "dropKey": null,
    "uniqueMod": null,
    "sellGold": 276154236,
    "cubeExp": 124303320
  }
}