{
  "id": 148001,
  "slug": "mithril-ore",
  "type": "MATERIAL",
  "name": {
    "zh": "秘银矿石",
    "en": "Mithril Ore"
  },
  "description": {
    "zh": "可以用来制作某物的最高级材料。",
    "en": "A premium material that can be used to craft something."
  },
  "icon": "/game/game/items/materials/Item_148001.png",
  "image": "/game/game/items/materials/Item_148001.png",
  "grade": "DIVINE",
  "gear": null,
  "level": null,
  "gameVersion": "game-v1",
  "updatedAt": "2026-06-03T11:43:00.360Z",
  "source": "local-json",
  "marketable": true,
  "removed": false,
  "confidence": "datamined",
  "detail": {
    "desc": {
      "zh-Hans": "可以用来制作某物的最高级材料。",
      "zh-Hant": "可以用來製作某物的最高級材料。",
      "en-US": "A premium material that can be used to craft something.",
      "fr-FR": "Un matériau de qualité supérieure pouvant être utilisé pour fabriquer quelque chose.",
      "de-DE": "Ein erstklassiges Material, das zur Herstellung von etwas verwendet werden kann.",
      "id-ID": "Material premium yang dapat digunakan untuk membuat sesuatu.",
      "ja-JP": "何かを作るのに使える最高級の素材。",
      "ko-KR": "무언가를 만들 수 있는 최고급 재료.",
      "pl-PL": "Najwyższej klasy materiał, który można użyć do stworzenia czegoś.",
      "pt-BR": "Um material premium que pode ser usado para criar algo.",
      "ru-RU": "Элитный материал, из которого можно что-нибудь создать.",
      "es-ES": "Un material premium que se puede usar para fabricar algo.",
      "th-TH": "วัสดุพรีเมียมที่สามารถใช้สร้างสิ่งของได้",
      "tr-TR": "Bir şeyler yapmak için kullanılabilecek premium bir malzeme.",
      "uk-UA": "Преміальний матеріал, з якого можна щось створити.",
      "vi-VN": "Nguyên liệu đặc biệt có thể dùng để chế tạo vật phẩm."
    },
    "stats": null,
    "synthType": "Material",
    "dropKey": null,
    "uniqueMod": null
  }
}